ezmsg/tools/__init__.py
ezmsg/tools/__version__.py
ezmsg/tools/dag.py
ezmsg/tools/proc.py
ezmsg/tools/perfmon/__init__.py
ezmsg/tools/perfmon/main.py
ezmsg/tools/shmem/__init__.py
ezmsg/tools/shmem/shmem.py
ezmsg/tools/shmem/shmem_mirror.py
ezmsg/tools/sigmon/__init__.py
ezmsg/tools/sigmon/main.py
ezmsg/tools/sigmon/ui/__init__.py
ezmsg/tools/sigmon/ui/base.py
ezmsg/tools/sigmon/ui/dag.py
ezmsg/tools/sigmon/ui/timeseries.py
ezmsg_tools-0.1.0.dist-info/METADATA
ezmsg_tools-0.1.0.dist-info/WHEEL
ezmsg_tools-0.1.0.dist-info/entry_points.txt
ezmsg_tools-0.1.0.dist-info/licenses/LICENSE
ezmsg_tools-0.1.0.dist-info/RECORD
