Metadata-Version: 2.4
Name: ezmsg-tools
Version: 0.1.0
Summary: ezmsg namespace package containing tools for working with ezmsg graphs.
Author-email: Chadwick Boulay <chadwick.boulay@gmail.com>
License-Expression: MIT
License-File: LICENSE
Requires-Python: >=3.10.15
Requires-Dist: ezmsg>=3.6.1
Requires-Dist: numpy>=1.26.0
Provides-Extra: perfmon
Requires-Dist: dash-bootstrap-components>=1.6.0; extra == 'perfmon'
Requires-Dist: dash-extensions>=1.0.19; extra == 'perfmon'
Requires-Dist: dash>=2.18.2; extra == 'perfmon'
Requires-Dist: ezmsg-baseproc; extra == 'perfmon'
Requires-Dist: pandas>=2.2.3; extra == 'perfmon'
Requires-Dist: plotly>=5.24.1; extra == 'perfmon'
Requires-Dist: pygtail>=0.14.0; extra == 'perfmon'
Requires-Dist: typer>=0.15.1; extra == 'perfmon'
Provides-Extra: sigmon
Requires-Dist: pygame>=2.6.1; extra == 'sigmon'
Requires-Dist: pygraphviz>=1.14; extra == 'sigmon'
Requires-Dist: typer>=0.15.1; extra == 'sigmon'
